zepben/protobuf/__init__.py
zepben/protobuf/cc/__init__.py
zepben/protobuf/cc/cc_data_pb2.py
zepben/protobuf/cc/cc_data_pb2.pyi
zepben/protobuf/cc/cc_data_pb2_grpc.py
zepben/protobuf/cc/cc_pb2.py
zepben/protobuf/cc/cc_pb2.pyi
zepben/protobuf/cc/cc_pb2_grpc.py
zepben/protobuf/cc/cc_requests_pb2.py
zepben/protobuf/cc/cc_requests_pb2.pyi
zepben/protobuf/cc/cc_requests_pb2_grpc.py
zepben/protobuf/cc/cc_responses_pb2.py
zepben/protobuf/cc/cc_responses_pb2.pyi
zepben/protobuf/cc/cc_responses_pb2_grpc.py
zepben/protobuf/cim/__init__.py
zepben/protobuf/cim/extensions/__init__.py
zepben/protobuf/cim/extensions/iec61968/__init__.py
zepben/protobuf/cim/extensions/iec61968/assetinfo/RelayInfo_pb2.py
zepben/protobuf/cim/extensions/iec61968/assetinfo/RelayInfo_pb2.pyi
zepben/protobuf/cim/extensions/iec61968/assetinfo/RelayInfo_pb2_grpc.py
zepben/protobuf/cim/extensions/iec61968/assetinfo/__init__.py
zepben/protobuf/cim/extensions/iec61968/common/ContactDetails_pb2.py
zepben/protobuf/cim/extensions/iec61968/common/ContactDetails_pb2.pyi
zepben/protobuf/cim/extensions/iec61968/common/ContactDetails_pb2_grpc.py
zepben/protobuf/cim/extensions/iec61968/common/ContactMethodType_pb2.py
zepben/protobuf/cim/extensions/iec61968/common/ContactMethodType_pb2.pyi
zepben/protobuf/cim/extensions/iec61968/common/ContactMethodType_pb2_grpc.py
zepben/protobuf/cim/extensions/iec61968/common/__init__.py
zepben/protobuf/cim/extensions/iec61968/metering/PanDemandResponseFunction_pb2.py
zepben/protobuf/cim/extensions/iec61968/metering/PanDemandResponseFunction_pb2.pyi
zepben/protobuf/cim/extensions/iec61968/metering/PanDemandResponseFunction_pb2_grpc.py
zepben/protobuf/cim/extensions/iec61968/metering/__init__.py
zepben/protobuf/cim/extensions/iec61970/__init__.py
zepben/protobuf/cim/extensions/iec61970/base/__init__.py
zepben/protobuf/cim/extensions/iec61970/base/core/HvCustomer_pb2.py
zepben/protobuf/cim/extensions/iec61970/base/core/HvCustomer_pb2.pyi
zepben_protobuf-1.2.0.dist-info/METADATA
zepben_protobuf-1.2.0.dist-info/WHEEL
zepben_protobuf-1.2.0.dist-info/top_level.txt
zepben_protobuf-1.2.0.dist-info/RECORD
