Metadata-Version: 2.4
Name: zepben.protobuf
Version: 1.2.0
Summary: EWB Python Protobuf and gRPC definitions
Author-email: Anthony Charlton <anthony.charlton@zepben.com>, Kurt Greaves <kurt.greaves@zepben.com>
Maintainer-email: Anthony Charlton <anthony.charlton@zepben.com>, Kurt Greaves <kurt.greaves@zepben.com>
License-Expression: MPL-2.0
Project-URL: GitHub, https://github.com/zepben/ewb-grpc
Classifier: Programming Language :: Python :: 3
Classifier: Programming Language :: Python :: 3.9
Classifier: Programming Language :: Python :: 3.10
Classifier: Programming Language :: Python :: 3.11
Classifier: Programming Language :: Python :: 3.12
Classifier: Operating System :: OS Independent
Requires-Python: >=3.9
Requires-Dist: protobuf==4.25.7
Requires-Dist: grpcio==1.61.3
Requires-Dist: grpcio-tools==1.61.3
Requires-Dist: pep517
Requires-Dist: pyyaml==6.0.3
Requires-Dist: gitpython
